xml2pytorch/__init__.py
xml2pytorch/converter.py
xml2pytorch-0.0.10.dist-info/LICENSE
xml2pytorch-0.0.10.dist-info/METADATA
xml2pytorch-0.0.10.dist-info/WHEEL
xml2pytorch-0.0.10.dist-info/top_level.txt
xml2pytorch-0.0.10.dist-info/RECORD
